{
    "observation": {
        "previous_period_summary": {
            "cnt_percentage": 84.21,
            "cnt_requests": 16,
            "losses_percentage": 0.0,
            "losses_volume": 0
        },
        "current_period": {
            "phase_one": [
                {
                    "protocolSessionId": "a8893bb6-4a1b-4b8a-af25-063ecf6d1639",
                    "account": 123123104,
                    "date": "2025-03-12T09:04:54.001",
                    "duration": 35130.0,
                    "used": 33338370,
                    "losses": 0,
                    "requests": 3,
                    "handler": "CNT"
                }
            ],
            "phase_two": [
                {
                    "protocolSessionId": "2a9703c0-b65d-4da2-a91b-5caf16ab9a80",
                    "account": 123123104,
                    "duration": 20,
                    "date": "2025-03-12T10:17:40.001",
                    "used": 1248605176,
                    "losses": 0,
                    "requests": 4,
                    "handler": "CTG"
                },
                {
                    "protocolSessionId": "2a8cb31f-7b4d-448f-b766-45c174f5aa39",
                    "account": 123123104,
                    "duration": 20,
                    "date": "2025-03-12T11:03:49.001",
                    "used": 368144,
                    "losses": 0,
                    "requests": 2,
                    "handler": "CTG"
                }
            ]
        }
    }
}