{
    "observation": {
        "previous_period_summary": {
            "cnt_percentage": 15.79,
            "cnt_requests": 6,
            "losses_percentage": 0.3484,
            "losses_volume": 5181104
        },
        "current_period": {
            "phase_one": [
                {
                    "protocolSessionId": "511914c6-cb36-4e5c-ac5e-91304b7b3ea5",
                    "account": 123123103,
                    "date": "2025-04-28T12:22:29.001",
                    "duration": 6.0,
                    "used": 24,
                    "losses": 0,
                    "requests": 3,
                    "handler": "CNT"
                },
                {
                    "protocolSessionId": "b7a44d35-46b7-44e9-bf68-68172be6a1bd",
                    "account": 123123103,
                    "date": "2025-04-28T18:57:58.001",
                    "duration": 2340.0,
                    "used": 2340,
                    "losses": 0,
                    "requests": 3,
                    "handler": "CNT"
                },
                {
                    "protocolSessionId": "efcd5977-2f68-4beb-894b-b231a88c2fb3",
                    "account": 123123103,
                    "date": "2025-04-28T22:49:08.001",
                    "duration": 9.0,
                    "used": 1742139,
                    "losses": 0,
                    "requests": 3,
                    "handler": "CNT"
                },
                {
                    "protocolSessionId": "8326229c-380b-4268-b2ef-69e73120c0ea",
                    "account": 123123103,
                    "date": "2025-04-28T23:21:03.001",
                    "duration": 73241.0,
                    "used": 107020150,
                    "losses": 0,
                    "requests": 6,
                    "handler": "CNT"
                }
            ],
            "phase_two": [
                {
                    "protocolSessionId": "41b44217-46bb-4b63-be4a-f09695ca5722",
                    "account": 123123103,
                    "duration": 20,
                    "date": "2025-04-29T15:01:38.001",
                    "used": 401227940,
                    "losses": 0,
                    "requests": 3,
                    "handler": "CTG"
                },
                {
                    "protocolSessionId": "827c2a3c-b1bd-488b-941b-3ce5aa0077f2",
                    "account": 123123103,
                    "duration": 20,
                    "date": "2025-04-29T18:25:35.001",
                    "used": 2529912,
                    "losses": 0,
                    "requests": 2,
                    "handler": "CTG"
                }
            ]
        }
    }
}