{
    "observation": {
        "previous_period_summary": {
            "cnt_percentage": 81.82,
            "cnt_requests": 9,
            "losses_percentage": 0.0,
            "losses_volume": 0
        },
        "current_period": {
            "phase_one": [
                {
                    "protocolSessionId": "75c73908-2e54-4856-ba0c-853177a15aef",
                    "account": 123123105,
                    "date": "2025-03-05T12:17:44.001",
                    "duration": 330.0,
                    "used": 2359170,
                    "losses": 0,
                    "requests": 3,
                    "handler": "CNT"
                }
            ],
            "phase_two": [
                {
                    "protocolSessionId": "5bde7e08-48c1-4d96-827c-2ae58a5c8892",
                    "account": 123123105,
                    "duration": 20,
                    "date": "2025-03-05T16:12:29.001",
                    "used": 66704850,
                    "losses": 0,
                    "requests": 2,
                    "handler": "CTG"
                },
                {
                    "protocolSessionId": "48e0cb14-4b70-4de1-b4fc-b9ad26ccfc1b",
                    "account": 123123105,
                    "duration": 20,
                    "date": "2025-03-06T09:44:36.001",
                    "used": 48494457,
                    "losses": 0,
                    "requests": 2,
                    "handler": "CTG"
                },
                {
                    "protocolSessionId": "b07a0496-2736-404b-956a-5659e89a2ca6",
                    "account": 123123105,
                    "duration": 20,
                    "date": "2025-03-06T10:39:41.001",
                    "used": 0,
                    "losses": 0,
                    "requests": 1,
                    "handler": "CTG"
                },
                {
                    "protocolSessionId": "aca9fc73-1905-42b8-85b6-866f026eb7f2",
                    "account": 123123105,
                    "duration": 20,
                    "date": "2025-03-06T13:06:42.001",
                    "used": 73990980,
                    "losses": 0,
                    "requests": 2,
                    "handler": "CTG"
                },
                {
                    "protocolSessionId": "0fc8c51a-12d5-47e5-8ef0-c4b2bb531f40",
                    "account": 123123105,
                    "duration": 20,
                    "date": "2025-03-06T13:18:13.001",
                    "used": 1901799,
                    "losses": 0,
                    "requests": 2,
                    "handler": "CTG"
                }
            ]
        }
    }
}